pygame_animations/__init__.py
pygame_animations/animation.py
pygame_animations/effects.py
pygame_animations/events.py
pygame_animations-1.2.1.dist-info/LICENSE
pygame_animations-1.2.1.dist-info/METADATA
pygame_animations-1.2.1.dist-info/WHEEL
pygame_animations-1.2.1.dist-info/top_level.txt
pygame_animations-1.2.1.dist-info/RECORD
