Metadata-Version: 2.1
Name: pygame-animations
Version: 1.2.1
Summary: An extension for pygame
Home-page: https://github.com/k39dev/pygame-animations
Author: K_39
Author-email: louisdevie@gmail.com
License: UNKNOWN
Platform: UNKNOWN
Classifier: Programming Language :: Python :: 3
Classifier: License :: OSI Approved :: MIT License
Classifier: Operating System :: OS Independent
Requires-Python: >=3.8
